[
  {
    "name": "AURELIEN",
    "seasonPoints": 13,
    "totalPoints": 125,
    "plePoints": 0,
    "rank": 1,
    "imageUrl": "cards/AURELIEN.png",
    "championDays": 350,
    "boostCount": 2,
    "pleHistory": [],
    "achievements": [
      {
        "title": "Champion WORLD PPW",
        "days": 181,
        "imageUrl": "achievements/world_champion.png"
      }
    ]
  },
  {
    "name": "BRANDON",
    "seasonPoints": 6,
    "totalPoints": 96,
    "plePoints": 0,
    "rank": 2,
    "imageUrl": "cards/BRANDON.png",
    "championDays": 0,
    "boostCount": 0,
    "pleHistory": [
      {
        "name": "Crown Jewel 2024",
        "points": 7
      }
    ],
    "achievements": [
      {
        "title": "Champion PLE",
        "days": 28,
        "imageUrl": "achievements/ple_champion.png"
      }
    ]
  },
  {
    "name": "MIZOU",
    "seasonPoints": 7,
    "totalPoints": 60,
    "plePoints": 0,
    "rank": 3,
    "imageUrl": "cards/MIZOU.png",
    "championDays": 0,
    "boostCount": 0,
    "pleHistory": [],
    "achievements": []
  },
  {
    "name": "FLO",
    "seasonPoints": 9,
    "totalPoints": 8,
    "plePoints": 1,
    "rank": 4,
    "imageUrl": "cards/FLO.png",
    "championDays": 0,
    "boostCount": 0,
    "pleHistory": [],
    "achievements": []
  },
  {
    "name": "NEK",
    "seasonPoints": 6,
    "totalPoints": 107,
    "plePoints": 0,
    "rank": 5,
    "imageUrl": "cards/NEK.png",
    "championDays": 0,
    "boostCount": 0,
    "pleHistory": [],
    "achievements": []
  },
  {
    "name": "MATHIS",
    "seasonPoints": 5,
    "totalPoints": 110,
    "plePoints": 0,
    "rank": 6,
    "imageUrl": "cards/MATHIS.png",
    "championDays": 151,
    "boostCount": 1,
    "pleHistory": [],
    "achievements": [
      {
        "title": "Champion ALL TIME PPW",
        "days": 151,
        "imageUrl": "achievements/all_time_champion.png"
      },
      {
        "title": "Champion WORLD PPW",
        "days": 48,
        "imageUrl": "achievements/world_champion.png"
      }
    ]
  },
  {
    "name": "ANTO",
    "seasonPoints": 9,
    "totalPoints": 116,
    "plePoints": 0,
    "rank": 7,
    "imageUrl": "cards/ANTO.png",
    "championDays": 0,
    "boostCount": 0,
    "pleHistory": [],
    "achievements": [
      {
        "title": "Champion PLE",
        "days": 56,
        "imageUrl": "achievements/ple_champion.png"
      }
    ]
  },
  {
    "name": "QUENTIN",
    "seasonPoints": 7,
    "totalPoints": 108,
    "plePoints": 0,
    "rank": 8,
    "imageUrl": "cards/QUENTIN.png",
    "championDays": 0,
    "boostCount": 0,
    "pleHistory": [],
    "achievements": [
      {
        "title": "Champion PLE",
        "days": 35,
        "imageUrl": "achievements/ple_champion.png"
      }
    ]
  },
  {
    "name": "NATHAN",
    "seasonPoints": 4,
    "totalPoints": 71,
    "plePoints": 0,
    "rank": 9,
    "imageUrl": "cards/NATHAN.png",
    "championDays": 0,
    "boostCount": 0,
    "pleHistory": [],
    "achievements": []
  },
  {
    "name": "PETRELOU",
    "seasonPoints": 4,
    "totalPoints": 21,
    "plePoints": 0,
    "rank": 10,
    "imageUrl": "cards/PETRELOU.png",
    "championDays": 0,
    "boostCount": 0,
    "pleHistory": [],
    "achievements": []
  },
  {
    "name": "ANGELITO",
    "seasonPoints": 6,
    "totalPoints": 8,
    "plePoints": 0,
    "rank": 11,
    "imageUrl": "cards/ANGELITO.png",
    "championDays": 0,
    "boostCount": 0,
    "pleHistory": [],
    "achievements": []
  },
  {
    "name": "JASON",
    "seasonPoints": 6,
    "totalPoints": 112,
    "plePoints": 0,
    "rank": 12,
    "imageUrl": "cards/JASON.png",
    "championDays": 0,
    "boostCount": 0,
    "pleHistory": [],
    "achievements": []
  },
  {
    "name": "ONI",
    "seasonPoints": 0,
    "totalPoints": 54,
    "plePoints": 0,
    "rank": 13,
    "imageUrl": "cards/ONI.png",
    "championDays": 0,
    "boostCount": 0,
    "pleHistory": [],
    "achievements": []
  },
  {
    "name": "RYOLAIT12",
    "seasonPoints": 0,
    "totalPoints": 29,
    "plePoints": 0,
    "rank": 14,
    "imageUrl": "cards/RYOLAIT12.png",
    "championDays": 0,
    "boostCount": 0,
    "pleHistory": [],
    "achievements": [
      {
        "title": "Champion PLE",
        "days": 27,
        "imageUrl": "achievements/ple_champion.png"
      }
    ]
  },
  {
    "name": "BEN",
    "seasonPoints": 0,
    "totalPoints": 38,
    "plePoints": 0,
    "rank": 15,
    "imageUrl": "cards/BEN.png",
    "championDays": 0,
    "boostCount": 0,
    "pleHistory": [],
    "achievements": []
  },
  {
    "name": "LUDOPOUL",
    "seasonPoints": 0,
    "totalPoints": 56,
    "plePoints": 0,
    "rank": 16,
    "imageUrl": "cards/LUDOPOUL.png",
    "championDays": 0,
    "boostCount": 0,
    "pleHistory": [],
    "achievements": []
  },
  {
    "name": "ELCHAPO",
    "seasonPoints": 0,
    "totalPoints": 10,
    "plePoints": 0,
    "rank": 17,
    "imageUrl": "cards/ELCHAPO.png",
    "championDays": 0,
    "boostCount": 0,
    "pleHistory": [],
    "achievements": []
  },
  {
    "name": "SHOOOTIX",
    "seasonPoints": 0,
    "totalPoints": 0,
    "plePoints": 0,
    "rank": 18,
    "imageUrl": "cards/SHOOOTIX.png",
    "championDays": 0,
    "boostCount": 0,
    "pleHistory": [],
    "achievements": []
  },
  {
    "name": "BLEMZER",
    "seasonPoints": 0,
    "totalPoints": 0,
    "plePoints": 0,
    "rank": 19,
    "imageUrl": "cards/BLEMZER.png",
    "championDays": 0,
    "boostCount": 0,
    "pleHistory": [],
    "achievements": []
  },
  {
    "name": "NEOZY",
    "seasonPoints": 0,
    "totalPoints": 0,
    "plePoints": 0,
    "rank": 20,
    "imageUrl": "cards/NEOZY.png",
    "championDays": 0,
    "boostCount": 0,
    "pleHistory": [],
    "achievements": []
  }
]